babbl/__init__.py
babbl/cli.py
babbl/defaults.py
babbl/elements.py
babbl/parser.py
babbl/renderer.py
babbl/util.py
babbl-0.2.9.dist-info/licenses/LICENSE
babbl-0.2.9.dist-info/METADATA
babbl-0.2.9.dist-info/WHEEL
babbl-0.2.9.dist-info/entry_points.txt
babbl-0.2.9.dist-info/top_level.txt
babbl-0.2.9.dist-info/RECORD
