Metadata-Version: 2.4
Name: babbl
Version: 0.2.9
Summary: Turn markdown into beautiful research blog posts
Author-email: Michael Lutz <michael@example.com>
License: MIT
Keywords: markdown,blog,research,static-site
Classifier: Development Status :: 3 - Alpha
Classifier: Intended Audience :: Developers
Classifier: License :: OSI Approved :: MIT License
Classifier: Programming Language :: Python :: 3
Classifier: Programming Language :: Python :: 3.8
Classifier: Programming Language :: Python :: 3.9
Classifier: Programming Language :: Python :: 3.10
Classifier: Programming Language :: Python :: 3.11
Classifier: Programming Language :: Python :: 3.12
Requires-Python: >=3.8
License-File: LICENSE
Requires-Dist: markdown>=3.4.0
Requires-Dist: pyyaml>=6.0
Requires-Dist: jinja2>=3.1.0
Requires-Dist: click>=8.1.0
Requires-Dist: pathspec>=0.11.0
Requires-Dist: watchdog>=3.0.0
Requires-Dist: pygments>=2.15.0
Requires-Dist: marko>=2.0.0
Provides-Extra: dev
Requires-Dist: pytest>=7.0.0; extra == "dev"
Requires-Dist: black>=23.0.0; extra == "dev"
Requires-Dist: flake8>=6.0.0; extra == "dev"
Requires-Dist: mypy>=1.0.0; extra == "dev"
Dynamic: license-file
